Metadata-Version: 2.1
Name: mlforall
Version: 0.3.3
Summary: Library that easily allows to create machine learning progress for more unexperiencied programmers.
Home-page: https://github.com/UnaiTorrecilla/MLForAll
Download-URL: https://github.com/UnaiTorrecilla/MLForAll/archive/refs/tags/v_033.tar.gz
Author: Unai Torrecilla
Author-email: unai.torrecilla@alumni.mondragon.edu
License: MIT
Keywords: Machine learning,Easy to use
Classifier: Development Status :: 5 - Production/Stable
Classifier: Intended Audience :: Developers
Classifier: Topic :: Software Development :: Build Tools
Classifier: License :: OSI Approved :: MIT License
Classifier: Programming Language :: Python :: 3.9
License-File: LICENSE
